mesh_os/.env.example
mesh_os/__init__.py
mesh_os/cli/commands.py
mesh_os/cli/main.py
mesh_os/core/__init__.py
mesh_os/core/client.py
mesh_os/core/taxonomy.py
mesh_os/py.typed
mesh_os/templates/.env.example
mesh_os/templates/docker-compose.yml
mesh_os/templates/examples/example.py
mesh_os/templates/examples/simple_example.py
mesh_os/templates/hasura/config.yaml
mesh_os/templates/hasura/metadata/config.yaml
mesh_os/templates/hasura/metadata/databases/databases.yaml
mesh_os/templates/hasura/metadata/databases/default/tables/public_agents.yaml
mesh_os/templates/hasura/metadata/databases/default/tables/public_memories.yaml
mesh_os/templates/hasura/metadata/databases/default/tables/public_memory_edges.yaml
mesh_os/templates/hasura/metadata/databases/default/tables/tables.yaml
mesh_os/templates/hasura/metadata/databases/default/tables/track_tables.yaml
mesh_os/templates/hasura/metadata/metadata.json
mesh_os/templates/hasura/metadata/version.yaml
mesh_os/templates/hasura/migrations/default/1_init/down.sql
mesh_os/templates/hasura/migrations/default/1_init/up.sql
mesh_os/templates/hasura/migrations/default/2_metadata_filtering/down.sql
mesh_os/templates/hasura/migrations/default/2_metadata_filtering/up.sql
mesh_os/templates/hasura/migrations/default/3_memory_expiry/down.sql
mesh_os/templates/hasura/migrations/default/3_memory_expiry/up.sql
mesh_os-0.1.11.dist-info/LICENSE
mesh_os-0.1.11.dist-info/METADATA
mesh_os-0.1.11.dist-info/WHEEL
mesh_os-0.1.11.dist-info/entry_points.txt
mesh_os-0.1.11.dist-info/RECORD
