Metadata-Version: 2.3
Name: mesh-os
Version: 0.1.11
Summary: MeshOS - A lightweight multi-agent memory system with semantic search
Keywords: ai,agents,memory,semantic-search,vector-database
Author: Calvin Hoenes
Author-email: calvin@props.app
Requires-Python: >=3.9,<4.0
Classifier: Development Status :: 4 - Beta
Classifier: Intended Audience :: Developers
Classifier: License :: OSI Approved :: MIT License
Classifier: Programming Language :: Python :: 3
Classifier: Programming Language :: Python :: 3.9
Classifier: Programming Language :: Python :: 3.10
Classifier: Programming Language :: Python :: 3.11
Classifier: Programming Language :: Python :: 3.12
Classifier: Programming Language :: Python :: 3.13
Classifier: Topic :: Software Development :: Libraries :: Python Modules
Requires-Dist: click (>=8.1.7,<9.0.0)
Requires-Dist: openai (>=1.12.0,<2.0.0)
Requires-Dist: pydantic (>=2.6.1,<3.0.0)
Requires-Dist: python-dotenv (>=1.0.0,<2.0.0)
Requires-Dist: requests (>=2.31.0,<3.0.0)
Requires-Dist: rich (>=13.7.0,<14.0.0)
Project-URL: Repository, https://github.com/Props-Labs/mesh-os
